fit/__init__.py
fit/fit.py
pyfit2-1.0.2.dist-info/LICENSE
pyfit2-1.0.2.dist-info/METADATA
pyfit2-1.0.2.dist-info/WHEEL
pyfit2-1.0.2.dist-info/top_level.txt
pyfit2-1.0.2.dist-info/RECORD
