Metadata-Version: 2.1
Name: pyfit2
Version: 1.0.2
Summary: erstelle varianzgewichteten Geraden-Fit
Author: Gabriel Remiszewski
Classifier: Programming Language :: Python :: 3
Classifier: License :: OSI Approved :: MIT License
Classifier: Operating System :: OS Independent
Requires-Python: >=3.9
License-File: LICENSE
